setup.py
hermes/Conflict.py
hermes/Grammar.py
hermes/GrammarAnalyzer.py
hermes/GrammarCodeGenerator.py
hermes/GrammarFileParser.py
hermes/Logger.py
hermes/Macro.py
hermes/Main.py
hermes/Morpheme.py
hermes/Theme.py
hermes/__init__.py
hermes_parser.egg-info/PKG-INFO
hermes_parser.egg-info/SOURCES.txt
hermes_parser.egg-info/dependency_links.txt
hermes_parser.egg-info/entry_points.txt
hermes_parser.egg-info/requires.txt
hermes_parser.egg-info/top_level.txt