Metadata-Version: 1.0
Name: hermes-parser
Version: 1.1
Summary: LL(1) parser generator with expression parsing support
Home-page: http://github.com/scottfrazer/hermes
Author: Scott Frazer
Author-email: scott.d.frazer@gmail.com
License: MIT
Keywords: Parser,Recursive Descent,LL(1),Pratt,Expression,Parser Generator
Platform: UNKNOWN
Classifier: License :: OSI Approved :: MIT License
Classifier: Programming Language :: Python
Classifier: Development Status :: 4 - Beta
Classifier: Intended Audience :: Developers
Classifier: Natural Language :: English
Classifier: Topic :: Software Development :: Code Generators
Classifier: Topic :: Software Development :: Compilers
